apertium2ud/__init__.py
apertium2ud/_map_processing.py
apertium2ud/convert.py
apertium2ud/meta.py
apertium2ud/resources/__init__.py
apertium2ud/resources/custom.udx
apertium2ud/resources/tags_map.json
apertium2ud-0.0.8.dist-info/LICENSE
apertium2ud-0.0.8.dist-info/METADATA
apertium2ud-0.0.8.dist-info/WHEEL
apertium2ud-0.0.8.dist-info/top_level.txt
apertium2ud-0.0.8.dist-info/RECORD
