Metadata-Version: 2.1
Name: apertium2ud
Version: 0.0.8
Summary: Converting universal tags to Apertium tags.
Home-page: https://github.com/alexeyev/apertium2ud
Author: Anton Alekseev
Author-email: anton.m.alexeye@gmail.com
Keywords: natural language processing,apertium,morphology
Classifier: Programming Language :: Python :: 3
Classifier: License :: OSI Approved :: GNU General Public License v3 (GPLv3)
Classifier: Operating System :: OS Independent
Classifier: Topic :: Text Processing
Requires-Python: >=3.7
License-File: LICENSE
